mwa_pulsar_client/__init__.py
mwa_pulsar_client/client.py
mwa_voltage-1.2.data/scripts/voltdownload.py
mwa_voltage-1.2.dist-info/LICENSE
mwa_voltage-1.2.dist-info/METADATA
mwa_voltage-1.2.dist-info/WHEEL
mwa_voltage-1.2.dist-info/top_level.txt
mwa_voltage-1.2.dist-info/RECORD
